aiowialon/__init__.py
aiowialon/accounts.py
aiowialon/client.py
aiowialon/exceptions.py
aiowialon/extensions.py
aiowialon/flags.py
aiowialon/messages.py
aiowialon/resources.py
aiowialon/units.py
aiowialon/utils.py
aiowialon-0.0.4b0.dist-info/LICENSE
aiowialon-0.0.4b0.dist-info/METADATA
aiowialon-0.0.4b0.dist-info/WHEEL
aiowialon-0.0.4b0.dist-info/entry_points.txt
aiowialon-0.0.4b0.dist-info/top_level.txt
aiowialon-0.0.4b0.dist-info/RECORD
